gpucore/__init__.py
gpucore/py.typed
gpucore-0.0.0.dist-info/WHEEL
gpucore-0.0.0.dist-info/METADATA
gpucore-0.0.0.dist-info/RECORD
