Metadata-Version: 2.4
Name: gpucore
Version: 0.0.0
Summary: GPU access from Python
Keywords: gpu,webgpu,wgpu,compute,graphics,rendering
Author: Willem Kokke
Author-email: Willem Kokke <mail@willem.net>
License-Expression: MIT
Classifier: Development Status :: 1 - Planning
Classifier: Intended Audience :: Developers
Classifier: License :: OSI Approved :: MIT License
Classifier: Programming Language :: Python :: 3
Classifier: Programming Language :: Python :: 3.9
Classifier: Programming Language :: Python :: 3.10
Classifier: Programming Language :: Python :: 3.11
Classifier: Programming Language :: Python :: 3.12
Classifier: Programming Language :: Python :: 3.13
Classifier: Topic :: Software Development :: Libraries
Requires-Python: >=3.9
Project-URL: Homepage, https://github.com/willemkokke/gpucore
Project-URL: Repository, https://github.com/willemkokke/gpucore
